hugomgmt/__init__.py
hugomgmt/hugo.py
hugomgmt/isso.py
hugomgmt/main.py
hugomgmt/openwebui.py
hugomgmt/shortcode.py
hugomgmt/shortcode_audio.py
hugomgmt/shortcode_csv.py
hugomgmt/shortcode_ignore.py
hugomgmt/shortcode_raw.py
hugomgmt/shortcode_tex.py
hugomgmt/staticsite.py
hugomgmt/util.py
hugomgmt/version.py
hugomgmt/wordpress.py
hugomgmt/template/multi-comment.mail.j2
hugomgmt/template/post-shortcode.md.j2
hugomgmt/template/post-toml.md.j2
hugomgmt/template/post.md.j2
hugomgmt/template/single-comment.mail.j2
hugomgmt-0.2.dist-info/LICENSE
hugomgmt-0.2.dist-info/METADATA
hugomgmt-0.2.dist-info/WHEEL
hugomgmt-0.2.dist-info/entry_points.txt
hugomgmt-0.2.dist-info/top_level.txt
hugomgmt-0.2.dist-info/zip-safe
hugomgmt-0.2.dist-info/RECORD
