Metadata-Version: 2.1
Name: hugomgmt
Version: 0.2
Summary: hugo static site management
Home-page: https://github.com/wtnb75/hugomgmt
Author: Watanabe Takashi
Author-email: wtnb75@gmail.com
License: MIT
Classifier: Development Status :: 3 - Alpha
Classifier: Intended Audience :: Developers
Classifier: License :: OSI Approved :: MIT License
Classifier: Topic :: Documentation
Classifier: Programming Language :: Python :: 3
License-File: LICENSE
Requires-Dist: markdownify <0.13
Requires-Dist: click
Requires-Dist: mysql-connector-python
Requires-Dist: jinja2
Requires-Dist: toml
Requires-Dist: PyYAML
Requires-Dist: feedendum
Requires-Dist: mdformat
Requires-Dist: mdformat-gfm
Requires-Dist: lxml
Requires-Dist: requests
Requires-Dist: emoji
Provides-Extra: ext
Requires-Dist: zopfli ; extra == 'ext'
Requires-Dist: brotli ; extra == 'ext'
